{"version":1,"resource":"vscode-remote://ssh-remote%2Bubuntu_22_04/home/ubuntu/Project-Agora/openvidu-tutorials/openvidu-react/src/components/Pages/DebateRoom/DebateRoom.jsx","entries":[{"id":"y6w8.jsx","timestamp":1732617830255},{"id":"klB9.jsx","source":"undoRedo.source","timestamp":1732617833118},{"id":"1WaT.jsx","timestamp":1732617839719},{"id":"QI3w.jsx","timestamp":1732618026491},{"id":"IKZa.jsx","source":"undoRedo.source","timestamp":1732618037136},{"id":"tdoF.jsx","timestamp":1732620174249},{"id":"YBvQ.jsx","source":"undoRedo.source","timestamp":1732620182459},{"id":"Kozi.jsx","timestamp":1732620395729},{"id":"qGEw.jsx","timestamp":1732620602746},{"id":"IXKE.jsx","timestamp":1732620661478},{"id":"RkZJ.jsx","timestamp":1732621078409},{"id":"ZNmL.jsx","timestamp":1732621111339},{"id":"oH3d.jsx","timestamp":1732621404086},{"id":"guP4.jsx","timestamp":1732621432185},{"id":"02sK.jsx","timestamp":1732621589258},{"id":"YrLV.jsx","timestamp":1732621628106},{"id":"yaii.jsx","timestamp":1732621647736},{"id":"HPKp.jsx","source":"undoRedo.source","timestamp":1732621694701},{"id":"0FVx.jsx","timestamp":1732621699968},{"id":"vTWD.jsx","timestamp":1732621921180},{"id":"zAOP.jsx","source":"undoRedo.source","timestamp":1732621922879},{"id":"2yQO.jsx","timestamp":1732622016628},{"id":"5dWM.jsx","timestamp":1732622044807},{"id":"udCA.jsx","timestamp":1732622069093},{"id":"rDuP.jsx","timestamp":1732622097240},{"id":"kj5s.jsx","timestamp":1732622141586},{"id":"EERg.jsx","timestamp":1732622171286},{"id":"M5sk.jsx","timestamp":1732622625364},{"id":"9vLz.jsx","timestamp":1732622648322},{"id":"Xhzo.jsx","timestamp":1732622700790},{"id":"Gh2a.jsx","timestamp":1732622723589},{"id":"KK2g.jsx","source":"undoRedo.source","timestamp":1732622738167},{"id":"Oapl.jsx","timestamp":1732622793103},{"id":"mtKs.jsx","timestamp":1732622989016},{"id":"ftF9.jsx","timestamp":1732623225118},{"id":"JgLJ.jsx","timestamp":1732623241318},{"id":"5RUM.jsx","timestamp":1732623260119},{"id":"qkvp.jsx","timestamp":1732623742269},{"id":"Rwz8.jsx","timestamp":1732623764245},{"id":"UA4r.jsx","timestamp":1732623780077},{"id":"3ba1.jsx","timestamp":1732628116603},{"id":"GsbE.jsx","timestamp":1732628185666},{"id":"6m5U.jsx","timestamp":1732682934586},{"id":"ulif.jsx","timestamp":1732683863586},{"id":"sqM7.jsx","source":"moved.source","sourceDescription":"~/Project-Agora/openvidu-tutorials/openvidu-react/src/components/Pages/DebateRoom/DebateRoom.jsx","timestamp":1732683952167},{"id":"sl3M.jsx","source":"moved.source","sourceDescription":"~/Project-Agora/openvidu-tutorials/openvidu-react/src/components/DebateRoom/DebateRoom.jsx","timestamp":1732683974084},{"id":"Y1F8.jsx","timestamp":1732684163135},{"id":"1EhG.jsx","source":"undoRedo.source","timestamp":1732684175345},{"id":"oFjJ.jsx","timestamp":1732684227159},{"id":"5as0.jsx","source":"undoRedo.source","timestamp":1732684582121}]}