{"version":1,"resource":"vscode-remote://ssh-remote%2Bubuntu_22_04/home/ubuntu/Project-Agora/openvidu-tutorials/openvidu-react/src/components/Pages/Room/Room.jsx","entries":[{"id":"m3IB.jsx","source":"작업 영역 편집","timestamp":1732339251152},{"id":"ooNm.jsx","timestamp":1732345864002},{"id":"wjq5.jsx","timestamp":1732429979469},{"id":"wfuF.jsx","source":"작업 영역 편집","timestamp":1732429985372},{"id":"3J84.jsx","timestamp":1732429987962},{"id":"Vlr7.jsx","source":"undoRedo.source","timestamp":1732429991847},{"id":"oaJf.jsx","timestamp":1732429993097},{"id":"Sm1n.jsx","timestamp":1732430009065},{"id":"9VUh.jsx","timestamp":1732430043965},{"id":"sOzw.jsx","timestamp":1732430065387},{"id":"Mi2E.jsx","timestamp":1732430089469},{"id":"Iwk4.jsx","source":"undoRedo.source","timestamp":1732430162397},{"id":"JxMP.jsx","timestamp":1732430202421},{"id":"wGay.jsx","timestamp":1732430221213},{"id":"eLnT.jsx","timestamp":1732433290439},{"id":"WzRY.jsx","timestamp":1732433309305},{"id":"IX0h.jsx","timestamp":1732433340859},{"id":"rV3w.jsx","source":"undoRedo.source","timestamp":1732433362638},{"id":"2opC.jsx","timestamp":1732433447670},{"id":"MfHR.jsx","timestamp":1732433458695},{"id":"8bW6.jsx","timestamp":1732433489857},{"id":"thUp.jsx","timestamp":1732434508869},{"id":"tJlx.jsx","timestamp":1732434559183},{"id":"7dYq.jsx","source":"undoRedo.source","timestamp":1732434613276},{"id":"26pu.jsx","timestamp":1732434616219},{"id":"wJXc.jsx","source":"undoRedo.source","timestamp":1732435170353},{"id":"Mi5g.jsx","timestamp":1732435191256},{"id":"mX5t.jsx","source":"작업 영역 편집","timestamp":1732435192498},{"id":"h1XD.jsx","timestamp":1732435193958},{"id":"6Hq3.jsx","timestamp":1732436285998},{"id":"vgnx.jsx","timestamp":1732514766914},{"id":"1sm1.jsx","timestamp":1732514819658},{"id":"R43C.jsx","timestamp":1732607558425},{"id":"0frJ.jsx","timestamp":1732607702838},{"id":"dHvl.jsx","timestamp":1732607718501},{"id":"6pbo.jsx","timestamp":1732607738474},{"id":"gPbt.jsx","source":"undoRedo.source","timestamp":1732607751836},{"id":"dIeF.jsx","timestamp":1732625002055}]}